setup.py
kivish/__init__.py
kivish/config.py
kivish/main.py
kivish.egg-info/PKG-INFO
kivish.egg-info/SOURCES.txt
kivish.egg-info/dependency_links.txt
kivish.egg-info/top_level.txt
kivish/generator/__init__.py
kivish/generator/config.py
kivish/generator/main.py
kivish/generator/test_generator.py
kivish/generator/utils.py
kivish/node/__init__.py
kivish/node/config.py
kivish/node/main.py
kivish/node/test_node.py
kivish/node/primary_nodes_locator/__init__.py
kivish/node/primary_nodes_locator/config.py
kivish/node/primary_nodes_locator/main.py
kivish/node/primary_nodes_locator/string_to_list.py
kivish/node/primary_nodes_locator/test_primary_nodes_locator.py
kivish/node/primary_nodes_locator/test_string_to_list.py
kivish/node/tree_builder/__init__.py
kivish/node/tree_builder/config.py
kivish/node/tree_builder/helpers.py
kivish/node/tree_builder/main.py
kivish/node/tree_builder/test_tree_builder.py
kivish/scanner/__init__.py
kivish/scanner/main.py
kivish/scripts/kivish
kivish/utils/__init__.py
kivish/utils/config.py
kivish/utils/error.py
kivish/utils/helper_value_reader.py
kivish/utils/line_info.py
kivish/utils/regex.py
kivish/utils/test_line_info.py