Metadata-Version: 1.0
Name: kivish
Version: 0.2.1
Summary: html template language
Home-page: https://gitlab.com/jligeza/kivish
Author: Jakub Ligęza
Author-email: jakub.jaroslaw.ligeza@gmail.com
License: MIT
Platform: UNKNOWN
